MianfeiLingquAliJishuZiliaoJiemi100BenDianzishuZhaoquanLeFix1/README.md
MianfeiLingquAliJishuZiliaoJiemi100BenDianzishuZhaoquanLeFix1/__init__.py
MianfeiLingquAliJishuZiliaoJiemi100BenDianzishuZhaoquanLeFix1/__main__.py
MianfeiLingquAliJishuZiliaoJiemi100BenDianzishuZhaoquanLeFix1/file.pdf
MianfeiLingquAliJishuZiliaoJiemi100BenDianzishuZhaoquanLeFix1/index.html
mianfei_lingqu_ali_jishu_ziliao_jiemi_100_ben_dianzishu_zhaoquan_le_fix1-2025.3.25.1.dist-info/METADATA
mianfei_lingqu_ali_jishu_ziliao_jiemi_100_ben_dianzishu_zhaoquan_le_fix1-2025.3.25.1.dist-info/WHEEL
mianfei_lingqu_ali_jishu_ziliao_jiemi_100_ben_dianzishu_zhaoquan_le_fix1-2025.3.25.1.dist-info/entry_points.txt
mianfei_lingqu_ali_jishu_ziliao_jiemi_100_ben_dianzishu_zhaoquan_le_fix1-2025.3.25.1.dist-info/top_level.txt
mianfei_lingqu_ali_jishu_ziliao_jiemi_100_ben_dianzishu_zhaoquan_le_fix1-2025.3.25.1.dist-info/RECORD
