Metadata-Version: 2.1
Name: mianfei-lingqu-ali-jishu-ziliao-jiemi-100-ben-dianzishu-zhaoquan-le-fix1
Version: 2025.3.25.1
Summary: 【免费领取】阿里技术资料解密，100 本电子书找全了
Home-page: https://github.com/apachecn/mianfei-lingqu-ali-jishu-ziliao-jiemi-100-ben-dianzishu-zhaoquan-le-fix1
Author: ApacheCN
Author-email: apachecn@163.com
Classifier: Development Status :: 4 - Beta
Classifier: Environment :: Console
Classifier: Intended Audience :: Developers
Classifier: Intended Audience :: End Users/Desktop
Classifier: License :: Other/Proprietary License
Classifier: Natural Language :: Chinese (Simplified)
Classifier: Natural Language :: English
Classifier: Operating System :: OS Independent
Classifier: Programming Language :: Python :: 3
Classifier: Programming Language :: Python :: 3 :: Only
Classifier: Programming Language :: Python :: 3.6
Classifier: Programming Language :: Python :: 3.7
Classifier: Topic :: Text Processing :: Markup :: Markdown
Classifier: Topic :: Text Processing :: Markup :: HTML
Classifier: Topic :: Internet :: WWW/HTTP
Classifier: Topic :: Software Development :: Documentation
Classifier: Topic :: Documentation
Requires-Python: >=3.6
